steamctl/__init__.py
steamctl/__main__.py
steamctl/argparser.py
steamctl/clients.py
steamctl/commands/__init__.py
steamctl/commands/apps/__init__.py
steamctl/commands/apps/enums.py
steamctl/commands/apps/gcmds.py
steamctl/commands/assistant/__init__.py
steamctl/commands/assistant/card_idler.py
steamctl/commands/assistant/discovery_queue.py
steamctl/commands/authenticator/__init__.py
steamctl/commands/authenticator/cmd_code.py
steamctl/commands/authenticator/cmds.py
steamctl/commands/clean/__init__.py
steamctl/commands/clean/cmds.py
steamctl/commands/cloud/__init__.py
steamctl/commands/cloud/gcmds.py
steamctl/commands/depot/__init__.py
steamctl/commands/depot/gcmds.py
steamctl/commands/hlmaster/__init__.py
steamctl/commands/hlmaster/cmds.py
steamctl/commands/steamid/__init__.py
steamctl/commands/steamid/cmds.py
steamctl/commands/ugc/__init__.py
steamctl/commands/ugc/gcmds.py
steamctl/commands/webapi/__init__.py
steamctl/commands/webapi/cmds.py
steamctl/commands/workshop/__init__.py
steamctl/commands/workshop/cmds.py
steamctl/commands/workshop/gcmds.py
steamctl/utils/__init__.py
steamctl/utils/apps.py
steamctl/utils/format.py
steamctl/utils/prompt.py
steamctl/utils/storage.py
steamctl/utils/tqdm.py
steamctl/utils/versions_report.py
steamctl/utils/web.py
steamctl-0.9.5.dist-info/LICENSE
steamctl-0.9.5.dist-info/METADATA
steamctl-0.9.5.dist-info/WHEEL
steamctl-0.9.5.dist-info/entry_points.txt
steamctl-0.9.5.dist-info/top_level.txt
steamctl-0.9.5.dist-info/zip-safe
steamctl-0.9.5.dist-info/RECORD
