Metadata-Version: 2.1
Name: steamctl
Version: 0.9.5
Summary: Take control of Steam from your terminal
Home-page: https://github.com/ValvePython/steamctl
Author: Rossen Georgiev
Author-email: rossen@rgp.io
License: MIT
Keywords: steam steamctl steamid steamcommunity authenticator workshop
Platform: UNKNOWN
Classifier: Development Status :: 4 - Beta
Classifier: Environment :: Console
Classifier: Natural Language :: English
Classifier: License :: OSI Approved :: MIT License
Classifier: Operating System :: OS Independent
Classifier: Programming Language :: Python :: 3.5
Classifier: Programming Language :: Python :: 3.6
Classifier: Programming Language :: Python :: 3.7
Classifier: Programming Language :: Python :: 3.8
Classifier: Programming Language :: Python :: 3.9
Requires-Python: ~=3.4
License-File: LICENSE
